cmplstyle/__init__.py
cmplstyle/_color_data.py
cmplstyle/colors.py
cmplstyle/mplstyle.rc
cmplstyle/utils.py
cmplstyle/assets/TCC_indexed_ncols_5.pdf
cmplstyle/assets/TCC_ncols_5.pdf
cmplstyle/assets/example_tcc_palette.png
cmplstyle/assets/linear_fitting_example.png
cmplstyle/fonts/SourceHanSerifSC-Medium.otf
cmplstyle/fonts/SourceHanSerifSC-SemiBold.otf
cmplstyle-0.7.0.dist-info/METADATA
cmplstyle-0.7.0.dist-info/WHEEL
cmplstyle-0.7.0.dist-info/licenses/LICENSE
cmplstyle-0.7.0.dist-info/RECORD
