Metadata-Version: 2.4
Name: cmplstyle
Version: 0.7.0
Summary: A Python package providing matplotlib style for scientific plotting with traditional Chinese color palette.
Project-URL: Homepage, https://github.com/jinyiliu/cmplstyle
Project-URL: Issues, https://github.com/jinyiliu/cmplstyle/issues
Author-email: Jinyi Liu <liujy0129@gmail.com>
Maintainer-email: Jinyi Liu <liujy0129@gmail.com>
License: MIT
License-File: LICENSE
Keywords: color palette,matplotlib,scientific plotting,traditional Chinese color
Classifier: Development Status :: 3 - Alpha
Classifier: Intended Audience :: Science/Research
Classifier: Operating System :: OS Independent
Classifier: Programming Language :: Python :: 3
Requires-Python: >=3.11
Requires-Dist: matplotlib>=3.7.0
